{
  "email": "",
  "expired_date": "2023-06-09",
  "fax": "",
  "ik_address": "634507, Томская область, Муниципальное образование \"Томский район\", Зональненское сельское поселение, п. Зональная Станция, ул. Совхозная, 10, Здание Администрации поселения",
  "ik_lat": 56.430624,
  "ik_lon": 85.012633,
  "ik_phone": "8-(3822)-923170",
  "info_url": "http://www.tomsk.vybory.izbirkom.ru/region/tomsk?action=ik&vrn=4704021284081",
  "persons": [
    {
      "person_name": "Григорьев Александр Владимирович",
      "recomend_by": "Региональное отделение Политической партии СПРАВЕДЛИВАЯ РОССИЯ в Томской области",
      "status": "Член"
    },
    {
      "person_name": "Дудин Виктор Андреевич",
      "recomend_by": "собрание избирателей по месту жительства",
      "status": "Член"
    },
    {
      "person_name": "Железнова Минжиян Идрисовна",
      "recomend_by": "собрание избирателей по месту работы",
      "status": "Член"
    },
    {
      "person_name": "Зелендинова Елена Валерьевна",
      "recomend_by": "Томское региональное отделение Политической партии ЛДПР - Либерально-демократическая партия России",
      "status": "Член"
    },
    {
      "person_name": "Козицына Анна Ивановна",
      "recomend_by": "собрание избирателей по месту работы",
      "status": "Зам.председателя"
    },
    {
      "person_name": "Маслянникова Галина Михайловна",
      "recomend_by": "Местное отделение Томского района Всероссийской политической партии \"ЕДИНАЯ РОССИЯ\"",
      "status": "Член"
    },
    {
      "person_name": "Мещук Яна Алексеевна",
      "recomend_by": "собрание избирателей по месту жительства",
      "status": "Член"
    },
    {
      "person_name": "Ночевная Елена Борисовна",
      "recomend_by": "собрание избирателей по месту жительства",
      "status": "Председатель"
    },
    {
      "person_name": "Пришмантайте Анна Леонидовна",
      "recomend_by": "собрание избирателей по месту жительства",
      "status": "Член"
    },
    {
      "person_name": "Рюмина Марина Владимировна",
      "recomend_by": "собрание избирателей по месту работы",
      "status": "Член"
    },
    {
      "person_name": "Цепляева Елена Сергеевна",
      "recomend_by": "Томское районное местное отделение Томского областного отделения политической партии \"Коммунистическая партия Российской Федерации\"",
      "status": "Член"
    },
    {
      "person_name": "Чернова Софья Михайловна",
      "recomend_by": "собрание избирателей по месту работы",
      "status": "Секретарь"
    },
    {
      "person_name": "Шараева Лариса Витальевна",
      "recomend_by": "собрание избирателей по месту жительства",
      "status": "Член"
    }
  ],
  "title": "Участковая избирательная комиссия №665",
  "voteroom_address": "634507, Томская область, Муниципальное образование \"Томский район\", Зональненское сельское поселение, п. Зональная Станция, ул. Совхозная, 16, Здание Дома культуры",
  "voteroom_lat": 56.430325,
  "voteroom_lon": 85.014385,
  "voteroom_phone": "8-(3822)-923075"
}