{
  "email": "",
  "expired_date": "2023-06-09",
  "fax": "",
  "ik_address": "634570, Томская область, Муниципальное образование \"Томский район\", Богашевское сельское поселение, д. Белоусово, ул. Мира, 8, Здание клуба-филиала",
  "ik_lat": 56.302682,
  "ik_lon": 85.182684,
  "ik_phone": "8-(923)-4433328",
  "info_url": "http://www.tomsk.vybory.izbirkom.ru/region/tomsk?action=ik&vrn=4704021284074",
  "persons": [
    {
      "person_name": "Белан Сергей Анатольевич",
      "recomend_by": "Томское районное местное отделение Томского областного отделения политической партии \"Коммунистическая партия Российской Федерации\"",
      "status": "Зам.председателя"
    },
    {
      "person_name": "Гадиева Елена Николаевна",
      "recomend_by": "Региональное отделение Политической партии СПРАВЕДЛИВАЯ РОССИЯ в Томской области",
      "status": "Председатель"
    },
    {
      "person_name": "Жирова Ольга Викторовна",
      "recomend_by": "Томское региональное отделение Политической партии ЛДПР - Либерально-демократическая партия России",
      "status": "Член"
    },
    {
      "person_name": "Степанов Захар Сергеевич",
      "recomend_by": "Местное отделение Томского района Всероссийской политической партии \"ЕДИНАЯ РОССИЯ\"",
      "status": "Секретарь"
    }
  ],
  "title": "Участковая избирательная комиссия №662",
  "voteroom_address": "634570, Томская область, Муниципальное образование \"Томский район\", Богашевское сельское поселение, д. Белоусово, ул. Мира, 8, Здание клуба-филиала",
  "voteroom_lat": 56.302682,
  "voteroom_lon": 85.182684,
  "voteroom_phone": "8-(923)-4433328"
}