{
  "email": "",
  "expired_date": "2023-06-07",
  "fax": "",
  "ik_address": "636200, Томская область, Бакчарский район, с.Бакчар, ул.Вицмана, 2, здание БФ ОГБПОУ \"КАПТ\"",
  "ik_lat": 57.023245,
  "ik_lon": 82.079588,
  "ik_phone": "8-(38249)-21-272",
  "info_url": "http://www.tomsk.vybory.izbirkom.ru/region/tomsk?action=ik&vrn=4704003138084",
  "persons": [
    {
      "person_name": "Агафонов Сергей Васильевич",
      "recomend_by": "собрание избирателей по месту работы",
      "status": "Член"
    },
    {
      "person_name": "Долгополова Ирина Абджалиевна",
      "recomend_by": "Томское региональное отделение Политической партии ЛДПР - Либерально-демократическая партия России",
      "status": "Зам.председателя"
    },
    {
      "person_name": "Кривошеина Яна Юрьевна",
      "recomend_by": "Региональное отделение Политической партии СПРАВЕДЛИВАЯ РОССИЯ в Томской области",
      "status": "Член"
    },
    {
      "person_name": "Кузнецов Владимир Михайлович",
      "recomend_by": "собрание избирателей по месту работы",
      "status": "Член"
    },
    {
      "person_name": "Курлович Наталья Анатольевна",
      "recomend_by": "Бакчарское местное отделение Всероссийской политической партии \"ЕДИНАЯ РОССИЯ\"",
      "status": "Председатель"
    },
    {
      "person_name": "Мясникова Нина Михайловна",
      "recomend_by": "собрание избирателей по месту работы",
      "status": "Член"
    },
    {
      "person_name": "Хмелевская Надежда Александровна",
      "recomend_by": "собрание избирателей по месту работы",
      "status": "Член"
    },
    {
      "person_name": "Шарабурова Любовь Федоровна",
      "recomend_by": "ТОМСКОЕ ОБЛАСТНОЕ ОТДЕЛЕНИЕ политической партии \"КОММУНИСТИЧЕСКАЯ ПАРТИЯ РОССИЙСКОЙ ФЕДЕРАЦИИ\"",
      "status": "Секретарь"
    }
  ],
  "title": "Участковая избирательная комиссия №387",
  "voteroom_address": "636200, Томская область, Бакчарский район, с.Бакчар, ул.Вицмана, 2, здание БФ ОГБПОУ \"КАПТ\"",
  "voteroom_lat": 57.023245,
  "voteroom_lon": 82.079588,
  "voteroom_phone": "8-(38249)-21-272"
}