{
  "email": "",
  "expired_date": "2023-06-08",
  "fax": "",
  "ik_address": "636785, Томская область, Муниципальное образование \"Город Стрежевой\", 4 микрорайон, 433/1, ОСК \"Десантник\", учебный класс",
  "ik_lat": 60.734401,
  "ik_lon": 77.613546,
  "ik_phone": "83825939622",
  "info_url": "http://www.tomsk.vybory.izbirkom.ru/region/tomsk?action=ik&vrn=4704015139403",
  "persons": [
    {
      "person_name": "Аладко Лейсан Камилевна",
      "recomend_by": "собрание избирателей по месту жительства",
      "status": "Секретарь"
    },
    {
      "person_name": "Аладко Сергей Александрович",
      "recomend_by": "собрание избирателей по месту работы",
      "status": "Председатель"
    },
    {
      "person_name": "Алексеева Анна Игоревна",
      "recomend_by": "Стрежевское местное отделение Томского областного отделения политической партии \"Коммунистическая партия Российской Федерации\"",
      "status": "Член"
    },
    {
      "person_name": "Борисова Людмила Алексеевна",
      "recomend_by": "Местное отделение г.Стрежевого Всероссийской политической партии \"ЕДИНАЯ РОССИЯ\"",
      "status": "Член"
    },
    {
      "person_name": "Кытина Татьяна Александровна",
      "recomend_by": "Томское региональное отделение Политической партии ЛДПР - Либерально-демократическая партия России",
      "status": "Член"
    },
    {
      "person_name": "Ланцова Людмила Владимировна",
      "recomend_by": "собрание избирателей по месту работы",
      "status": "Зам.председателя"
    },
    {
      "person_name": "Леконцева Наталья Владимировна",
      "recomend_by": "собрание избирателей по месту работы",
      "status": "Член"
    },
    {
      "person_name": "Усольцева Людмила Анатоьевна",
      "recomend_by": "Региональное отделение Политической партии СПРАВЕДЛИВАЯ РОССИЯ в Томской области",
      "status": "Член"
    },
    {
      "person_name": "Черных Евгения Владимировна",
      "recomend_by": "собрание избирателей по месту работы",
      "status": "Член"
    }
  ],
  "title": "Участковая избирательная комиссия №360",
  "voteroom_address": "636785, Томская область, Муниципальное образование \"Город Стрежевой\", 4 микрорайон, 433/1, ОСК \"Десантник\", учебный класс",
  "voteroom_lat": 60.734401,
  "voteroom_lon": 77.613546,
  "voteroom_phone": "83825939622"
}